stealthkit/__init__.py
stealthkit/stealth.py
stealthkit-1.0.3.dist-info/METADATA
stealthkit-1.0.3.dist-info/WHEEL
stealthkit-1.0.3.dist-info/top_level.txt
stealthkit-1.0.3.dist-info/RECORD
