Metadata-Version: 2.4
Name: stealthkit
Version: 1.0.3
Summary: A stealthy HTTP request library with rotating user agents and proxy support
Home-page: https://github.com/theonlyanil/stealthkit
Author: Anil Sardiwal
Author-email: theonlyanil@gmail.com
Classifier: Programming Language :: Python :: 3
Classifier: License :: OSI Approved :: MIT License
Classifier: Operating System :: OS Independent
Requires-Python: >=3.6
Requires-Dist: curl-cffi==0.10.0
Requires-Dist: fake-useragent==2.0.3
Dynamic: author
Dynamic: author-email
Dynamic: classifier
Dynamic: description
Dynamic: description-content-type
Dynamic: home-page
Dynamic: requires-dist
Dynamic: requires-python
Dynamic: summary
